basex/__init__.py
basex/alphabet.py
basex/base11.py
basex/base2.py
basex/base32.py
basex/base32z.py
basex/base36.py
basex/base58.py
basex/base62.py
basex/base64.py
basex/base67.py
basex/base8.py
base_x-1.3.dist-info/METADATA
base_x-1.3.dist-info/WHEEL
base_x-1.3.dist-info/licenses/AUTHORS
base_x-1.3.dist-info/licenses/LICENSE
base_x-1.3.dist-info/RECORD
