Metadata-Version: 2.1
Name: base-x
Version: 1.3
Summary: Encoding/decoding of any given alphabet with any base using bitcoin style
Project-URL: Homepage, https://github.com/ayum/ayum.basex
Project-URL: Bug Tracker, https://github.com/ayum/ayum.basex/issues
Author: Aleksey Mikhaylov
License-Expression: MIT
License-File: AUTHORS
License-File: LICENSE
Classifier: Development Status :: 5 - Production/Stable
Classifier: Environment :: Console
Classifier: Intended Audience :: Developers
Classifier: License :: OSI Approved :: MIT License
Classifier: Operating System :: OS Independent
Classifier: Programming Language :: Python :: 3
Classifier: Topic :: Software Development :: Libraries
Classifier: Topic :: Utilities
Requires-Python: >=3.10
